edgeml_pytorch/__init__.py
edgeml_pytorch/utils.py
edgeml_pytorch/graph/__init__.py
edgeml_pytorch/graph/bonsai.py
edgeml_pytorch/graph/protoNN.py
edgeml_pytorch/graph/rnn.py
edgeml_pytorch/trainer/__init__.py
edgeml_pytorch/trainer/bonsaiTrainer.py
edgeml_pytorch/trainer/fastTrainer.py
edgeml_pytorch/trainer/fastmodel.py
edgeml_pytorch/trainer/protoNNTrainer.py
edgeml_pytorch/trainer/srnnTrainer.py
edgeml_pytorch-0.3.0.dist-info/METADATA
edgeml_pytorch-0.3.0.dist-info/WHEEL
edgeml_pytorch-0.3.0.dist-info/top_level.txt
edgeml_pytorch-0.3.0.dist-info/RECORD
