Metadata-Version: 2.1
Name: edgeml-pytorch
Version: 0.3.0
Summary: PyTorch code for ML algorithms for edge devices developed at Microsoft Research India.
Home-page: https://github.com/Microsoft/EdgeML
Author-email: edgeml@microsoft.com
License: MIT License
Platform: UNKNOWN
